autoloadm.py
setup.py
autoloadm.egg-info/PKG-INFO
autoloadm.egg-info/SOURCES.txt
autoloadm.egg-info/dependency_links.txt
autoloadm.egg-info/not-zip-safe
autoloadm.egg-info/top_level.txt